code_extractor/__init__.py
code_extractor/extracted_code.py
code_extractor/extractor/__init__.py
code_extractor/extractor/extract.py
code_extractor/extractor/literals.py
code_extractor/loader/__init__.py
code_extractor/loader/load.py
code_extractor/pickle/__init__.py
code_extractor/pickle/pickle_code.py
code_extractor-0.4.1.dist-info/LICENSE
code_extractor-0.4.1.dist-info/METADATA
code_extractor-0.4.1.dist-info/WHEEL
code_extractor-0.4.1.dist-info/top_level.txt
code_extractor-0.4.1.dist-info/RECORD
