Metadata-Version: 2.1
Name: code-extractor
Version: 0.4.1
Summary: Extract source code from python objects
Home-page: https://github.com/MatteoH2O1999/python_code_extractor
Author: MatteoH2O1999
Author-email: dellacqua.matteo99@gmail.com
Project-URL: Bug Tracker, https://github.com/MatteoH2O1999/python_code_extractor/issues
Classifier: Programming Language :: Python :: 3 :: Only
Classifier: Programming Language :: Python :: 3.7
Classifier: Programming Language :: Python :: 3.8
Classifier: Programming Language :: Python :: 3.9
Classifier: Programming Language :: Python :: 3.10
Classifier: Programming Language :: Python :: 3.11
Classifier: License :: OSI Approved :: GNU Affero General Public License v3
Classifier: Operating System :: OS Independent
Requires-Python: >=3.7
License-File: LICENSE
